ff_containers_sort/__init__.py
ff_containers_sort/ff_containers_sort.py
ff_containers_sort-1.5.2.dist-info/LICENSE
ff_containers_sort-1.5.2.dist-info/METADATA
ff_containers_sort-1.5.2.dist-info/WHEEL
ff_containers_sort-1.5.2.dist-info/entry_points.txt
ff_containers_sort-1.5.2.dist-info/top_level.txt
ff_containers_sort-1.5.2.dist-info/RECORD
