Metadata-Version: 2.1
Name: ff-containers-sort
Version: 1.5.2
Summary: Sorts Firefox Containers
Home-page: https://github.com/naamancampbell/ff-containers-sort
Author: Naaman Campbell
Author-email: naaman@clancampbell.id.au
License: UNKNOWN
Platform: UNKNOWN
Classifier: Programming Language :: Python :: 3
Classifier: License :: OSI Approved :: MIT License
Classifier: Operating System :: POSIX :: Linux
Classifier: Operating System :: Microsoft :: Windows
Classifier: Operating System :: MacOS
Requires-Python: >=3.6
